expert_intelligence_toolbox/__init__.py
expert_intelligence_toolbox/geographic.py
expert_intelligence_toolbox/snowflake_connector.py
expert_intelligence_toolbox/transform.py
expert_intelligence_toolbox-1.0.21.dist-info/METADATA
expert_intelligence_toolbox-1.0.21.dist-info/WHEEL
expert_intelligence_toolbox-1.0.21.dist-info/licenses/LICENSE
expert_intelligence_toolbox-1.0.21.dist-info/RECORD
